dj_paginator-0.2.1.dist-info/DESCRIPTION.rst
dj_paginator-0.2.1.dist-info/METADATA
dj_paginator-0.2.1.dist-info/metadata.json
dj_paginator-0.2.1.dist-info/RECORD
dj_paginator-0.2.1.dist-info/top_level.txt
dj_paginator-0.2.1.dist-info/WHEEL
paginator/__init__.py
paginator/models.py
paginator/paginators.py
paginator/templates/paginator/bootstrap/paginator.html
paginator/templates/paginator/foundation/paginator.html
paginator/templatetags/__init__.py
paginator/templatetags/paginator_tags.py
