Metadata-Version: 2.0
Name: dj-paginator
Version: 0.2.1
Summary: A super-simple set of pagination tools for Django 1.8+
Home-page: https://github.com/pydanny/dj-paginator
Author: Daniel Roy Greenfeld
Author-email: pydanny@gmail.com
License: BSD
Keywords: dj-paginator
Platform: UNKNOWN
Classifier: Development Status :: 2 - Pre-Alpha
Classifier: Framework :: Django
Classifier: Intended Audience :: Developers
Classifier: License :: OSI Approved :: BSD License
Classifier: Natural Language :: English
Classifier: Programming Language :: Python :: 2
Classifier: Programming Language :: Python :: 2.7
Classifier: Programming Language :: Python :: 3
Classifier: Programming Language :: Python :: 3.4
